pyPublicDecompWT.cpython-310-x86_64-linux-gnu.so
pyPublicDecompWT-2.8.1.6.data/scripts/xRITDecompress
pyPublicDecompWT-2.8.1.6.dist-info/RECORD
pyPublicDecompWT-2.8.1.6.dist-info/WHEEL
pyPublicDecompWT-2.8.1.6.dist-info/LICENSE
pyPublicDecompWT-2.8.1.6.dist-info/top_level.txt
pyPublicDecompWT-2.8.1.6.dist-info/AUTHORS.txt
pyPublicDecompWT-2.8.1.6.dist-info/METADATA
