Metadata-Version: 2.1
Name: pyPublicDecompWT
Version: 2.8.1.6
Summary: Python bindings for EUMETSAT's PublicDecompWT
Home-page: https://github.com/sbrodehl/pyPublicDecompWT
Author: Sebastian Brodehl
Author-email: foss@sbrodehl.de
License: Apache-2.0 License
Project-URL: Documentation, https://github.com/sbrodehl/pyPublicDecompWT
Project-URL: Source, https://github.com/sbrodehl/pyPublicDecompWT
Project-URL: Tracker, https://github.com/sbrodehl/pyPublicDecompWT/issues
Classifier: Development Status :: 4 - Beta
Classifier: Natural Language :: English
Classifier: License :: OSI Approved :: Apache Software License
Classifier: Operating System :: MacOS :: MacOS X
Classifier: Operating System :: POSIX :: Linux
Classifier: Programming Language :: Python
Classifier: Programming Language :: Python :: 3 :: Only
Classifier: Programming Language :: Python :: 3
Classifier: Programming Language :: Python :: 3.7
Classifier: Programming Language :: Python :: 3.8
Classifier: Programming Language :: Python :: 3.9
Classifier: Programming Language :: Python :: 3.10
Classifier: Programming Language :: Python :: 3.11
Classifier: Programming Language :: Python :: 3.12
Classifier: Programming Language :: Python :: 3.13
Classifier: Intended Audience :: Developers
Classifier: Intended Audience :: Science/Research
Classifier: Topic :: Scientific/Engineering :: Atmospheric Science
Classifier: Topic :: Scientific/Engineering :: Image Processing
Requires-Python: >=3.7
License-File: LICENSE
License-File: AUTHORS.txt
Provides-Extra: test
Requires-Dist: pytest ; extra == 'test'
